torand/__init__.py
torand/__main__.py
torand/torand.py
torand-0.0.2.dist-info/LICENSE
torand-0.0.2.dist-info/METADATA
torand-0.0.2.dist-info/WHEEL
torand-0.0.2.dist-info/entry_points.txt
torand-0.0.2.dist-info/top_level.txt
torand-0.0.2.dist-info/zip-safe
torand-0.0.2.dist-info/RECORD
