Metadata-Version: 2.1
Name: torand
Version: 0.0.2
Summary: Derive real random bytes from time differences between the executions of the code, implemented in python.
Home-page: https://github.com/hfxunlp/torand
Author: Hongfei Xu
Author-email: hfxunlp@foxmail.com
Maintainer: Hongfei Xu
Maintainer-email: hfxunlp@foxmail.com
License: GNU General Public License v3 (GPLv3)
Keywords: real random bytes
Classifier: License :: OSI Approved :: GNU General Public License v3 (GPLv3)
Classifier: Programming Language :: Python
Classifier: Topic :: Software Development :: Libraries :: Python Modules
Classifier: Topic :: Scientific/Engineering
Classifier: Topic :: Security :: Cryptography
Classifier: Topic :: Utilities
License-File: LICENSE
